hindiPOS/__init__.py
hindiPOS/bipos.csv
hindiPOS/hmm.py
hindiPOS/wdpos.csv
hindiPOS-0.0.6.dist-info/LICENSE.txt
hindiPOS-0.0.6.dist-info/METADATA
hindiPOS-0.0.6.dist-info/WHEEL
hindiPOS-0.0.6.dist-info/top_level.txt
hindiPOS-0.0.6.dist-info/RECORD
