Metadata-Version: 2.1
Name: hindiPOS
Version: 0.0.6
Summary: A small example package
Author: Devanshi
Author-email: Devanshi <devanshiisuri@gmail.com>
Classifier: Programming Language :: Python :: 3
Classifier: License :: OSI Approved :: MIT License
Classifier: Operating System :: OS Independent
Requires-Python: >=3.9
License-File: LICENSE.txt
Requires-Dist: polars
Requires-Dist: regex
